prefect_shell/__init__.py
prefect_shell/_version.py
prefect_shell/commands.py
prefect_shell-0.2.6.dist-info/LICENSE
prefect_shell-0.2.6.dist-info/METADATA
prefect_shell-0.2.6.dist-info/WHEEL
prefect_shell-0.2.6.dist-info/entry_points.txt
prefect_shell-0.2.6.dist-info/top_level.txt
prefect_shell-0.2.6.dist-info/RECORD
